{
  "meta": {
    "tipo": "ranking_total",
    "escopo": "federal/camara",
    "periodo": {
      "tipo": "mes",
      "ano": 2026,
      "mes": 2,
      "recorte": {
        "tipo": "uf",
        "valor": "BA"
      }
    },
    "geradoEm": "2026-03-03T15:29:12.765611Z",
    "versaoSchema": "1.1.0",
    "versaoCategoryMap": "1.0.0",
    "criterio": {
      "consideraAtivosNoPeriodo": true
    }
  },
  "itens": [
    {
      "id": 204553,
      "nome": "Pastor Sargento Isidório",
      "uf": "BA",
      "partido": "AVANTE",
      "valor": 400.0,
      "qtdLancamentos": 3
    },
    {
      "id": 178854,
      "nome": "Elmar Nascimento",
      "uf": "BA",
      "partido": "UNIÃO",
      "valor": 515.11,
      "qtdLancamentos": 2
    },
    {
      "id": 220696,
      "nome": "Ivoneide Caetano",
      "uf": "BA",
      "partido": "PT",
      "valor": 526.51,
      "qtdLancamentos": 2
    },
    {
      "id": 160610,
      "nome": "Valmir Assunção",
      "uf": "BA",
      "partido": "PT",
      "valor": 845.92,
      "qtdLancamentos": 5
    },
    {
      "id": 178858,
      "nome": "Mário Negromonte Jr.",
      "uf": "BA",
      "partido": "PP",
      "valor": 1250.47,
      "qtdLancamentos": 2
    },
    {
      "id": 160553,
      "nome": "Antonio Brito",
      "uf": "BA",
      "partido": "PSD",
      "valor": 1369.79,
      "qtdLancamentos": 5
    },
    {
      "id": 204567,
      "nome": "Raimundo Costa",
      "uf": "BA",
      "partido": "PODE",
      "valor": 1563.04,
      "qtdLancamentos": 10
    },
    {
      "id": 220693,
      "nome": "Roberta Roma",
      "uf": "BA",
      "partido": "PL",
      "valor": 1900.71,
      "qtdLancamentos": 6
    },
    {
      "id": 178860,
      "nome": "Paulo Azi",
      "uf": "BA",
      "partido": "UNIÃO",
      "valor": 3200.0,
      "qtdLancamentos": 2
    },
    {
      "id": 220694,
      "nome": "Ricardo Maia",
      "uf": "BA",
      "partido": "MDB",
      "valor": 3598.36,
      "qtdLancamentos": 10
    }
  ]
}