{
  "meta": {
    "tipo": "ranking_integridade",
    "escopo": "federal/camara",
    "periodo": {
      "tipo": "mes",
      "ano": 2023,
      "mes": 9
    },
    "geradoEm": "2026-03-04T12:35:21.112516Z",
    "versaoSchema": "1.0.0",
    "versaoCategoryMap": "1.0.0",
    "criterio": {
      "consideraAtivosNoPeriodo": true
    },
    "metrica": "valorSemDocumentoPdf"
  },
  "itens": [
    {
      "id": 141485,
      "nome": "Luiz Carlos Busato",
      "uf": "RS",
      "partido": "UNIÃO",
      "valor": 78655.18,
      "qtdLancamentos": 50,
      "qtdSemDocumentoPdf": 44
    },
    {
      "id": 74356,
      "nome": "Silas Câmara",
      "uf": "AM",
      "partido": "REPUBLICANOS",
      "valor": 77935.84,
      "qtdLancamentos": 14,
      "qtdSemDocumentoPdf": 13
    },
    {
      "id": 220645,
      "nome": "Erika Hilton",
      "uf": "SP",
      "partido": "PSOL",
      "valor": 61578.09,
      "qtdLancamentos": 143,
      "qtdSemDocumentoPdf": 53
    },
    {
      "id": 220677,
      "nome": "Keniston Braga",
      "uf": "PA",
      "partido": "MDB",
      "valor": 55274.4,
      "qtdLancamentos": 58,
      "qtdSemDocumentoPdf": 51
    },
    {
      "id": 74057,
      "nome": "Alice Portugal",
      "uf": "BA",
      "partido": "PCdoB",
      "valor": 47917.38,
      "qtdLancamentos": 26,
      "qtdSemDocumentoPdf": 26
    },
    {
      "id": 74858,
      "nome": "Lindbergh Farias",
      "uf": "RJ",
      "partido": "PT",
      "valor": 41531.5,
      "qtdLancamentos": 54,
      "qtdSemDocumentoPdf": 50
    },
    {
      "id": 74383,
      "nome": "Giacobo",
      "uf": "PR",
      "partido": "PL",
      "valor": 40962.91,
      "qtdLancamentos": 8,
      "qtdSemDocumentoPdf": 7
    },
    {
      "id": 204427,
      "nome": "Fernando Rodolfo",
      "uf": "PE",
      "partido": "PL",
      "valor": 39627.3,
      "qtdLancamentos": 59,
      "qtdSemDocumentoPdf": 53
    },
    {
      "id": 220604,
      "nome": "Marcos Tavares",
      "uf": "RJ",
      "partido": "PDT",
      "valor": 38251.63,
      "qtdLancamentos": 79,
      "qtdSemDocumentoPdf": 77
    },
    {
      "id": 160604,
      "nome": "Pedro Uczai",
      "uf": "SC",
      "partido": "PT",
      "valor": 33530.5,
      "qtdLancamentos": 142,
      "qtdSemDocumentoPdf": 79
    }
  ]
}