{
  "meta": {
    "tipo": "ranking_categoria",
    "escopo": "federal/camara",
    "categoriaQC": "PASSAGENS",
    "periodo": {
      "tipo": "mes",
      "ano": 2024,
      "mes": 11
    },
    "geradoEm": "2026-03-01T02:26:59.611218Z",
    "versaoSchema": "1.0.0",
    "versaoCategoryMap": "1.0.0",
    "criterio": {
      "consideraAtivosNoPeriodo": true
    }
  },
  "itens": [
    {
      "id": 74161,
      "nome": "Reginaldo Lopes",
      "uf": "MG",
      "partido": "PT",
      "valor": 45834.21,
      "qtdLancamentos": 46
    },
    {
      "id": 72442,
      "nome": "Felipe Carreras",
      "uf": "PE",
      "partido": "PSB",
      "valor": 43908.93,
      "qtdLancamentos": 67
    },
    {
      "id": 74858,
      "nome": "Lindbergh Farias",
      "uf": "RJ",
      "partido": "PT",
      "valor": 37525.31,
      "qtdLancamentos": 39
    },
    {
      "id": 204450,
      "nome": "Doutor Luizinho",
      "uf": "RJ",
      "partido": "PP",
      "valor": 36923.18,
      "qtdLancamentos": 44
    },
    {
      "id": 74158,
      "nome": "Mário Heringer",
      "uf": "MG",
      "partido": "PDT",
      "valor": 36704.71,
      "qtdLancamentos": 21
    },
    {
      "id": 74079,
      "nome": "José Priante",
      "uf": "PA",
      "partido": "MDB",
      "valor": 35427.02,
      "qtdLancamentos": 26
    },
    {
      "id": 204495,
      "nome": "Airton Faleiro",
      "uf": "PA",
      "partido": "PT",
      "valor": 32863.11,
      "qtdLancamentos": 45
    },
    {
      "id": 160510,
      "nome": "Luis Tibé",
      "uf": "MG",
      "partido": "AVANTE",
      "valor": 32001.1,
      "qtdLancamentos": 78
    },
    {
      "id": 141450,
      "nome": "Hugo Leal",
      "uf": "RJ",
      "partido": "PSD",
      "valor": 31200.39,
      "qtdLancamentos": 69
    },
    {
      "id": 74075,
      "nome": "Elcione Barbalho",
      "uf": "PA",
      "partido": "MDB",
      "valor": 30803.94,
      "qtdLancamentos": 44
    },
    {
      "id": 204462,
      "nome": "Chris Tonietto",
      "uf": "RJ",
      "partido": "PL",
      "valor": 28924.94,
      "qtdLancamentos": 93
    },
    {
      "id": 220667,
      "nome": "Pedro Campos",
      "uf": "PE",
      "partido": "PSB",
      "valor": 28787.91,
      "qtdLancamentos": 53
    },
    {
      "id": 220584,
      "nome": "Murilo Galdino",
      "uf": "PB",
      "partido": "REPUBLICANOS",
      "valor": 28774.28,
      "qtdLancamentos": 40
    },
    {
      "id": 220661,
      "nome": "Matheus Noronha",
      "uf": "CE",
      "partido": "PL",
      "valor": 28667.27,
      "qtdLancamentos": 24
    },
    {
      "id": 220674,
      "nome": "Dra. Alessandra Haber",
      "uf": "PA",
      "partido": "MDB",
      "valor": 28198.49,
      "qtdLancamentos": 23
    },
    {
      "id": 74554,
      "nome": "José Rocha",
      "uf": "BA",
      "partido": "UNIÃO",
      "valor": 27933.7,
      "qtdLancamentos": 22
    },
    {
      "id": 74784,
      "nome": "Luiza Erundina",
      "uf": "SP",
      "partido": "PSOL",
      "valor": 27773.45,
      "qtdLancamentos": 49
    },
    {
      "id": 220573,
      "nome": "Dorinaldo Malafaia",
      "uf": "AP",
      "partido": "PDT",
      "valor": 27622.64,
      "qtdLancamentos": 39
    },
    {
      "id": 178931,
      "nome": "Luciano Ducci",
      "uf": "PR",
      "partido": "PSB",
      "valor": 27164.52,
      "qtdLancamentos": 90
    },
    {
      "id": 141555,
      "nome": "Vinicius Carvalho",
      "uf": "SP",
      "partido": "REPUBLICANOS",
      "valor": 26167.56,
      "qtdLancamentos": 45
    },
    {
      "id": 178910,
      "nome": "Joaquim Passarinho",
      "uf": "PA",
      "partido": "PL",
      "valor": 25942.96,
      "qtdLancamentos": 38
    },
    {
      "id": 74428,
      "nome": "Mendonça Filho",
      "uf": "PE",
      "partido": "UNIÃO",
      "valor": 25739.98,
      "qtdLancamentos": 42
    },
    {
      "id": 204427,
      "nome": "Fernando Rodolfo",
      "uf": "PE",
      "partido": "PL",
      "valor": 25488.84,
      "qtdLancamentos": 44
    },
    {
      "id": 220540,
      "nome": "Duda Ramos",
      "uf": "RR",
      "partido": "MDB",
      "valor": 25325.7,
      "qtdLancamentos": 22
    },
    {
      "id": 160674,
      "nome": "Hugo Motta",
      "uf": "PB",
      "partido": "REPUBLICANOS",
      "valor": 25199.66,
      "qtdLancamentos": 56
    },
    {
      "id": 160512,
      "nome": "Aureo Ribeiro",
      "uf": "RJ",
      "partido": "SOLIDARIEDADE",
      "valor": 25121.78,
      "qtdLancamentos": 28
    },
    {
      "id": 160553,
      "nome": "Antonio Brito",
      "uf": "BA",
      "partido": "PSD",
      "valor": 24998.46,
      "qtdLancamentos": 67
    },
    {
      "id": 74478,
      "nome": "Luciano Bivar",
      "uf": "PE",
      "partido": "UNIÃO",
      "valor": 24143.5,
      "qtdLancamentos": 37
    },
    {
      "id": 220578,
      "nome": "Josenildo",
      "uf": "AP",
      "partido": "PDT",
      "valor": 24077.38,
      "qtdLancamentos": 36
    },
    {
      "id": 178989,
      "nome": "Renata Abreu",
      "uf": "SP",
      "partido": "PODE",
      "valor": 24049.3,
      "qtdLancamentos": 32
    },
    {
      "id": 160558,
      "nome": "Paulo Freire Costa",
      "uf": "SP",
      "partido": "PL",
      "valor": 23952.79,
      "qtdLancamentos": 26
    },
    {
      "id": 74356,
      "nome": "Silas Câmara",
      "uf": "AM",
      "partido": "REPUBLICANOS",
      "valor": 23657.25,
      "qtdLancamentos": 20
    },
    {
      "id": 204549,
      "nome": "AJ Albuquerque",
      "uf": "CE",
      "partido": "PP",
      "valor": 23503.99,
      "qtdLancamentos": 11
    },
    {
      "id": 204365,
      "nome": "Gilson Marques",
      "uf": "SC",
      "partido": "NOVO",
      "valor": 23472.53,
      "qtdLancamentos": 37
    },
    {
      "id": 220598,
      "nome": "Tarcísio Motta",
      "uf": "RJ",
      "partido": "PSOL",
      "valor": 23425.0,
      "qtdLancamentos": 82
    },
    {
      "id": 220586,
      "nome": "Rafael Brito",
      "uf": "AL",
      "partido": "MDB",
      "valor": 22630.03,
      "qtdLancamentos": 51
    },
    {
      "id": 139285,
      "nome": "Lídice da Mata",
      "uf": "BA",
      "partido": "PSB",
      "valor": 22348.24,
      "qtdLancamentos": 97
    },
    {
      "id": 204408,
      "nome": "Gustinho Ribeiro",
      "uf": "SE",
      "partido": "REPUBLICANOS",
      "valor": 22342.9,
      "qtdLancamentos": 19
    },
    {
      "id": 178854,
      "nome": "Elmar Nascimento",
      "uf": "BA",
      "partido": "UNIÃO",
      "valor": 22300.62,
      "qtdLancamentos": 28
    },
    {
      "id": 74262,
      "nome": "Carlos Sampaio",
      "uf": "SP",
      "partido": "PSD",
      "valor": 22293.34,
      "qtdLancamentos": 41
    },
    {
      "id": 178857,
      "nome": "Jorge Solla",
      "uf": "BA",
      "partido": "PT",
      "valor": 22269.49,
      "qtdLancamentos": 87
    },
    {
      "id": 160632,
      "nome": "Zé Silva",
      "uf": "MG",
      "partido": "SOLIDARIEDADE",
      "valor": 22249.53,
      "qtdLancamentos": 50
    },
    {
      "id": 220669,
      "nome": "Lula da Fonte",
      "uf": "PE",
      "partido": "PP",
      "valor": 22025.19,
      "qtdLancamentos": 87
    },
    {
      "id": 141458,
      "nome": "João Carlos Bacelar",
      "uf": "BA",
      "partido": "PL",
      "valor": 22018.71,
      "qtdLancamentos": 39
    },
    {
      "id": 220620,
      "nome": "Rosângela Reis",
      "uf": "MG",
      "partido": "PL",
      "valor": 21751.49,
      "qtdLancamentos": 30
    },
    {
      "id": 220616,
      "nome": "Luciano Vieira",
      "uf": "RJ",
      "partido": "PSDB",
      "valor": 21718.98,
      "qtdLancamentos": 27
    },
    {
      "id": 160527,
      "nome": "Aguinaldo Ribeiro",
      "uf": "PB",
      "partido": "PP",
      "valor": 21669.39,
      "qtdLancamentos": 49
    },
    {
      "id": 220650,
      "nome": "Paulo Alexandre Barbosa",
      "uf": "SP",
      "partido": "PSDB",
      "valor": 21657.56,
      "qtdLancamentos": 23
    },
    {
      "id": 179001,
      "nome": "Márcio Biolchi",
      "uf": "RS",
      "partido": "MDB",
      "valor": 21595.67,
      "qtdLancamentos": 55
    },
    {
      "id": 220672,
      "nome": "Henderson Pinto",
      "uf": "PA",
      "partido": "MDB",
      "valor": 21564.64,
      "qtdLancamentos": 25
    },
    {
      "id": 204367,
      "nome": "Daniel Freitas",
      "uf": "SC",
      "partido": "PL",
      "valor": 21383.19,
      "qtdLancamentos": 71
    },
    {
      "id": 74041,
      "nome": "Luiz Couto",
      "uf": "PB",
      "partido": "PT",
      "valor": 21318.25,
      "qtdLancamentos": 57
    },
    {
      "id": 220552,
      "nome": "Zucco",
      "uf": "RS",
      "partido": "PL",
      "valor": 21224.66,
      "qtdLancamentos": 41
    },
    {
      "id": 204472,
      "nome": "José Medeiros",
      "uf": "MT",
      "partido": "PL",
      "valor": 21120.87,
      "qtdLancamentos": 71
    },
    {
      "id": 220691,
      "nome": "Diego Coronel",
      "uf": "BA",
      "partido": "PSD",
      "valor": 21019.88,
      "qtdLancamentos": 53
    },
    {
      "id": 204535,
      "nome": "Sâmia Bomfim",
      "uf": "SP",
      "partido": "PSOL",
      "valor": 20956.37,
      "qtdLancamentos": 28
    },
    {
      "id": 178946,
      "nome": "Soraya Santos",
      "uf": "RJ",
      "partido": "PL",
      "valor": 20943.09,
      "qtdLancamentos": 35
    },
    {
      "id": 160552,
      "nome": "Danrlei de Deus Hinterholz",
      "uf": "RS",
      "partido": "PSD",
      "valor": 20694.69,
      "qtdLancamentos": 46
    },
    {
      "id": 220645,
      "nome": "Erika Hilton",
      "uf": "SP",
      "partido": "PSOL",
      "valor": 20587.51,
      "qtdLancamentos": 36
    },
    {
      "id": 178929,
      "nome": "Diego Garcia",
      "uf": "PR",
      "partido": "REPUBLICANOS",
      "valor": 20456.62,
      "qtdLancamentos": 100
    },
    {
      "id": 220640,
      "nome": "Juliana Cardoso",
      "uf": "SP",
      "partido": "PT",
      "valor": 20279.48,
      "qtdLancamentos": 92
    },
    {
      "id": 153423,
      "nome": "Renilce Nicodemos",
      "uf": "PA",
      "partido": "MDB",
      "valor": 19607.56,
      "qtdLancamentos": 22
    },
    {
      "id": 171617,
      "nome": "Paulão",
      "uf": "AL",
      "partido": "PT",
      "valor": 19292.37,
      "qtdLancamentos": 45
    },
    {
      "id": 141431,
      "nome": "Fernando Coelho Filho",
      "uf": "PE",
      "partido": "UNIÃO",
      "valor": 19272.7,
      "qtdLancamentos": 37
    },
    {
      "id": 73441,
      "nome": "Celso Russomanno",
      "uf": "SP",
      "partido": "REPUBLICANOS",
      "valor": 19202.18,
      "qtdLancamentos": 63
    },
    {
      "id": 74156,
      "nome": "Leonardo Monteiro",
      "uf": "MG",
      "partido": "PT",
      "valor": 19167.12,
      "qtdLancamentos": 31
    },
    {
      "id": 220561,
      "nome": "Delegada Katarina",
      "uf": "SE",
      "partido": "PSD",
      "valor": 19067.15,
      "qtdLancamentos": 52
    },
    {
      "id": 198197,
      "nome": "Greyce Elias",
      "uf": "MG",
      "partido": "AVANTE",
      "valor": 19039.64,
      "qtdLancamentos": 66
    },
    {
      "id": 221148,
      "nome": "Alfredinho",
      "uf": "SP",
      "partido": "PT",
      "valor": 18929.08,
      "qtdLancamentos": 33
    },
    {
      "id": 178866,
      "nome": "Luizianne Lins",
      "uf": "CE",
      "partido": "PT",
      "valor": 18919.75,
      "qtdLancamentos": 47
    },
    {
      "id": 220615,
      "nome": "Pastor Henrique Vieira",
      "uf": "RJ",
      "partido": "PSOL",
      "valor": 18825.54,
      "qtdLancamentos": 38
    },
    {
      "id": 220563,
      "nome": "Icaro de Valmir",
      "uf": "SE",
      "partido": "PL",
      "valor": 18692.05,
      "qtdLancamentos": 45
    },
    {
      "id": 220605,
      "nome": "Bandeira de Mello",
      "uf": "RJ",
      "partido": "PSB",
      "valor": 18486.04,
      "qtdLancamentos": 76
    },
    {
      "id": 220549,
      "nome": "Any Ortiz",
      "uf": "RS",
      "partido": "CIDADANIA",
      "valor": 18443.14,
      "qtdLancamentos": 34
    },
    {
      "id": 141518,
      "nome": "Paulinho da Força",
      "uf": "SP",
      "partido": "SOLIDARIEDADE",
      "valor": 17940.54,
      "qtdLancamentos": 39
    },
    {
      "id": 220559,
      "nome": "Julia Zanatta",
      "uf": "SC",
      "partido": "PL",
      "valor": 17767.21,
      "qtdLancamentos": 60
    },
    {
      "id": 226837,
      "nome": "Saulo Pedroso",
      "uf": "SP",
      "partido": "PSD",
      "valor": 17570.62,
      "qtdLancamentos": 68
    },
    {
      "id": 204498,
      "nome": "Olival Marques",
      "uf": "PA",
      "partido": "MDB",
      "valor": 17385.54,
      "qtdLancamentos": 13
    },
    {
      "id": 178927,
      "nome": "Aliel Machado",
      "uf": "PR",
      "partido": "PV",
      "valor": 17343.3,
      "qtdLancamentos": 36
    },
    {
      "id": 221338,
      "nome": "Professora Luciene Cavalcante",
      "uf": "SP",
      "partido": "PSOL",
      "valor": 17338.65,
      "qtdLancamentos": 58
    },
    {
      "id": 220585,
      "nome": "Mersinho Lucena",
      "uf": "PB",
      "partido": "PP",
      "valor": 17295.15,
      "qtdLancamentos": 34
    },
    {
      "id": 204409,
      "nome": "Daniel Trzeciak",
      "uf": "RS",
      "partido": "PSDB",
      "valor": 17104.13,
      "qtdLancamentos": 64
    },
    {
      "id": 204456,
      "nome": "Gutemberg Reis",
      "uf": "RJ",
      "partido": "MDB",
      "valor": 17074.12,
      "qtdLancamentos": 40
    },
    {
      "id": 204464,
      "nome": "Talíria Petrone",
      "uf": "RJ",
      "partido": "PSOL",
      "valor": 17057.92,
      "qtdLancamentos": 33
    },
    {
      "id": 160976,
      "nome": "Tiririca",
      "uf": "SP",
      "partido": "PSD",
      "valor": 17024.24,
      "qtdLancamentos": 17
    },
    {
      "id": 180214,
      "nome": "Pastor Diniz",
      "uf": "RR",
      "partido": "UNIÃO",
      "valor": 16964.39,
      "qtdLancamentos": 42
    },
    {
      "id": 160588,
      "nome": "Diego Andrade",
      "uf": "MG",
      "partido": "PSD",
      "valor": 16941.29,
      "qtdLancamentos": 31
    },
    {
      "id": 220653,
      "nome": "Fábio Teruel",
      "uf": "SP",
      "partido": "MDB",
      "valor": 16933.28,
      "qtdLancamentos": 46
    },
    {
      "id": 141464,
      "nome": "José Airton Félix Cirilo",
      "uf": "CE",
      "partido": "PT",
      "valor": 16894.05,
      "qtdLancamentos": 20
    },
    {
      "id": 220647,
      "nome": "Mauricio Neves",
      "uf": "SP",
      "partido": "PP",
      "valor": 16746.41,
      "qtdLancamentos": 22
    },
    {
      "id": 214694,
      "nome": "Jorge Goetten",
      "uf": "SC",
      "partido": "REPUBLICANOS",
      "valor": 16663.04,
      "qtdLancamentos": 54
    },
    {
      "id": 160548,
      "nome": "Jonas Donizette",
      "uf": "SP",
      "partido": "PSB",
      "valor": 16539.83,
      "qtdLancamentos": 74
    },
    {
      "id": 220621,
      "nome": "Sargento Gonçalves",
      "uf": "RN",
      "partido": "PL",
      "valor": 16470.11,
      "qtdLancamentos": 23
    },
    {
      "id": 220582,
      "nome": "Daniel Barbosa",
      "uf": "AL",
      "partido": "PP",
      "valor": 16205.45,
      "qtdLancamentos": 42
    },
    {
      "id": 204572,
      "nome": "Capitão Alberto Neto",
      "uf": "AM",
      "partido": "PL",
      "valor": 16121.72,
      "qtdLancamentos": 22
    },
    {
      "id": 220564,
      "nome": "Yandra Moura",
      "uf": "SE",
      "partido": "UNIÃO",
      "valor": 16021.74,
      "qtdLancamentos": 20
    },
    {
      "id": 204480,
      "nome": "Rogério Correia",
      "uf": "MG",
      "partido": "PT",
      "valor": 16014.64,
      "qtdLancamentos": 78
    },
    {
      "id": 98615,
      "nome": "Ismael",
      "uf": "SC",
      "partido": "PSD",
      "valor": 15920.36,
      "qtdLancamentos": 48
    },
    {
      "id": 141516,
      "nome": "Paulo Abi-Ackel",
      "uf": "MG",
      "partido": "PSDB",
      "valor": 15874.0,
      "qtdLancamentos": 59
    },
    {
      "id": 92699,
      "nome": "Fernando Monteiro",
      "uf": "PE",
      "partido": "PSD",
      "valor": 15767.98,
      "qtdLancamentos": 36
    }
  ]
}