{
  "meta": {
    "scope": "federal/camara",
    "type": "entity-profile",
    "generatedAt": "2026-03-16T09:02:10.491547Z",
    "schemaVersion": "1.0.0"
  },
  "entity": {
    "id": 220576,
    "name": "Alfredo Gaspar",
    "stateCode": "AL",
    "party": "UNIÃO",
    "photoUrl": "https://www.camara.leg.br/internet/deputado/bandep/220576.jpg"
  },
  "mandateTotals": {
    "amountNet": 1380497.03,
    "amountGross": 1449042.9,
    "amountAdjustments": -68545.87,
    "recordsCount": 787,
    "byCategoryNet": {
      "ALIMENTACAO": 0.0,
      "COMBUSTIVEL": 76948.74,
      "CONSULTORIA_SERVICOS": 0.0,
      "CORREIOS_TELEFONIA": 0.0,
      "DESLOCAMENTO": 424185.52,
      "DIVULGACAO": 791298.0,
      "ESCRITORIO": 88064.77,
      "HOSPEDAGEM": 0.0,
      "OUTROS": 0.0
    },
    "byCategoryGross": {
      "ALIMENTACAO": 0.0,
      "COMBUSTIVEL": 76948.74,
      "CONSULTORIA_SERVICOS": 0.0,
      "CORREIOS_TELEFONIA": 0.0,
      "DESLOCAMENTO": 492731.39,
      "DIVULGACAO": 791298.0,
      "ESCRITORIO": 88064.77,
      "HOSPEDAGEM": 0.0,
      "OUTROS": 0.0
    },
    "byCategoryAdjustments": {
      "ALIMENTACAO": 0.0,
      "COMBUSTIVEL": 0.0,
      "CONSULTORIA_SERVICOS": 0.0,
      "CORREIOS_TELEFONIA": 0.0,
      "DESLOCAMENTO": -68545.87,
      "DIVULGACAO": 0.0,
      "ESCRITORIO": 0.0,
      "HOSPEDAGEM": 0.0,
      "OUTROS": 0.0
    }
  },
  "yearTotals": {
    "2023": 387585.36,
    "2024": 443444.18,
    "2025": 490635.35,
    "2026": 58832.14
  },
  "monthTotals": {
    "2023-01": 0.0,
    "2023-02": 26545.73,
    "2023-03": 46918.79,
    "2023-04": 30651.02,
    "2023-05": 33778.26,
    "2023-06": 32853.66,
    "2023-07": 30487.42,
    "2023-08": 38484.38,
    "2023-09": 42430.31,
    "2023-10": 36045.11,
    "2023-11": 32026.71,
    "2023-12": 37363.97,
    "2024-01": 31162.43,
    "2024-02": 28997.72,
    "2024-03": 33388.55,
    "2024-04": 30118.96,
    "2024-05": 45530.57,
    "2024-06": 36859.6,
    "2024-07": 36933.71,
    "2024-08": 38236.1,
    "2024-09": 36279.73,
    "2024-10": 41266.44,
    "2024-11": 43494.93,
    "2024-12": 41175.44,
    "2025-01": 38444.31,
    "2025-02": 43492.32,
    "2025-03": 42654.16,
    "2025-04": 47457.47,
    "2025-05": 38315.91,
    "2025-06": 45288.66,
    "2025-07": 45799.6,
    "2025-08": 36219.0,
    "2025-09": 30576.0,
    "2025-10": 47434.64,
    "2025-11": 38972.13,
    "2025-12": 35981.15,
    "2026-01": 28850.7,
    "2026-02": 29981.44,
    "2026-03": 0.0,
    "2026-04": 0.0,
    "2026-05": 0.0,
    "2026-06": 0.0,
    "2026-07": 0.0,
    "2026-08": 0.0,
    "2026-09": 0.0,
    "2026-10": 0.0,
    "2026-11": 0.0,
    "2026-12": 0.0
  }
}