{
  "meta": {
    "scope": "federal/camara",
    "type": "entity-profile",
    "entityId": 220554,
    "generatedAt": "2026-04-19T05:43:02.354420Z",
    "schemaVersion": "1.0.0"
  },
  "entity": {
    "id": 220554,
    "name": "Alexandre Lindenmeyer",
    "stateCode": "RS",
    "party": "PT",
    "photoUrl": "https://www.camara.leg.br/internet/deputado/bandep/220554.jpg",
    "slug": "alexandre-lindenmeyer"
  },
  "mandateTotals": {
    "amountNet": 1579624.14,
    "amountGross": 1610955.24,
    "amountAdjustments": -31331.1,
    "recordsCount": 6285,
    "byCategoryNet": {
      "ALIMENTACAO": 19586.27,
      "COMBUSTIVEL": 265727.53,
      "CONSULTORIA_SERVICOS": 0.0,
      "CORREIOS_TELEFONIA": 56077.33,
      "DESLOCAMENTO": 736496.47,
      "DIVULGACAO": 122233.67,
      "ESCRITORIO": 334727.41,
      "HOSPEDAGEM": 44775.46,
      "OUTROS": 0.0
    },
    "byCategoryGross": {
      "ALIMENTACAO": 19586.27,
      "COMBUSTIVEL": 265727.53,
      "CONSULTORIA_SERVICOS": 0.0,
      "CORREIOS_TELEFONIA": 56077.33,
      "DESLOCAMENTO": 767827.57,
      "DIVULGACAO": 122233.67,
      "ESCRITORIO": 334727.41,
      "HOSPEDAGEM": 44775.46,
      "OUTROS": 0.0
    },
    "byCategoryAdjustments": {
      "ALIMENTACAO": 0.0,
      "COMBUSTIVEL": 0.0,
      "CONSULTORIA_SERVICOS": 0.0,
      "CORREIOS_TELEFONIA": 0.0,
      "DESLOCAMENTO": -31331.1,
      "DIVULGACAO": 0.0,
      "ESCRITORIO": 0.0,
      "HOSPEDAGEM": 0.0,
      "OUTROS": 0.0
    }
  },
  "yearTotals": {
    "2023": 521917.27,
    "2024": 447374.58,
    "2025": 511172.2,
    "2026": 99160.09
  },
  "monthTotals": {
    "2023-01": 0.0,
    "2023-02": 25034.73,
    "2023-03": 47768.05,
    "2023-04": 40736.18,
    "2023-05": 52328.49,
    "2023-06": 45154.0,
    "2023-07": 46649.88,
    "2023-08": 69107.93,
    "2023-09": 49070.04,
    "2023-10": 52984.74,
    "2023-11": 60641.27,
    "2023-12": 32441.96,
    "2024-01": 32530.23,
    "2024-02": 51514.38,
    "2024-03": 57927.55,
    "2024-04": 60805.99,
    "2024-05": 32283.34,
    "2024-06": 46003.56,
    "2024-07": 35397.85,
    "2024-08": 29840.66,
    "2024-09": 36317.89,
    "2024-10": 20283.33,
    "2024-11": 27403.48,
    "2024-12": 17066.32,
    "2025-01": 17501.04,
    "2025-02": 31573.41,
    "2025-03": 35458.08,
    "2025-04": 43505.18,
    "2025-05": 52438.12,
    "2025-06": 50478.17,
    "2025-07": 41294.05,
    "2025-08": 37902.98,
    "2025-09": 47703.48,
    "2025-10": 49358.74,
    "2025-11": 55034.63,
    "2025-12": 48924.32,
    "2026-01": 34297.17,
    "2026-02": 27639.32,
    "2026-03": 32916.27,
    "2026-04": 4307.33
  },
  "topCategory": {
    "category": "DESLOCAMENTO",
    "amountNet": 736496.47,
    "percent": 46.62
  }
}