{
  "meta": {
    "scope": "federal/camara",
    "type": "entity-profile",
    "entityId": 220631,
    "generatedAt": "2026-04-19T05:43:02.375533Z",
    "schemaVersion": "1.0.0"
  },
  "entity": {
    "id": 220631,
    "name": "Samuel Viana",
    "stateCode": "MG",
    "party": "UNIÃO",
    "photoUrl": "https://www.camara.leg.br/internet/deputado/bandep/220631.jpg",
    "slug": "samuel-viana"
  },
  "mandateTotals": {
    "amountNet": 1584634.89,
    "amountGross": 1629132.56,
    "amountAdjustments": -44497.67,
    "recordsCount": 2870,
    "byCategoryNet": {
      "ALIMENTACAO": 16767.79,
      "COMBUSTIVEL": 218167.57,
      "CONSULTORIA_SERVICOS": 0.0,
      "CORREIOS_TELEFONIA": 8213.87,
      "DESLOCAMENTO": 757725.08,
      "DIVULGACAO": 2032.9,
      "ESCRITORIO": 531116.42,
      "HOSPEDAGEM": 50611.26,
      "OUTROS": 0.0
    },
    "byCategoryGross": {
      "ALIMENTACAO": 16767.79,
      "COMBUSTIVEL": 218167.57,
      "CONSULTORIA_SERVICOS": 0.0,
      "CORREIOS_TELEFONIA": 8213.87,
      "DESLOCAMENTO": 802222.75,
      "DIVULGACAO": 2032.9,
      "ESCRITORIO": 531116.42,
      "HOSPEDAGEM": 50611.26,
      "OUTROS": 0.0
    },
    "byCategoryAdjustments": {
      "ALIMENTACAO": 0.0,
      "COMBUSTIVEL": 0.0,
      "CONSULTORIA_SERVICOS": 0.0,
      "CORREIOS_TELEFONIA": 0.0,
      "DESLOCAMENTO": -44497.67,
      "DIVULGACAO": 0.0,
      "ESCRITORIO": 0.0,
      "HOSPEDAGEM": 0.0,
      "OUTROS": 0.0
    }
  },
  "yearTotals": {
    "2023": 487297.51,
    "2024": 531390.64,
    "2025": 491057.04,
    "2026": 74889.7
  },
  "monthTotals": {
    "2023-01": 0.0,
    "2023-02": 43705.2,
    "2023-03": 39740.79,
    "2023-04": 46750.34,
    "2023-05": 50193.58,
    "2023-06": 47935.5,
    "2023-07": 52515.64,
    "2023-08": 49694.27,
    "2023-09": 55637.87,
    "2023-10": 44774.06,
    "2023-11": 36805.71,
    "2023-12": 19544.55,
    "2024-01": 40684.0,
    "2024-02": 45172.96,
    "2024-03": 42091.31,
    "2024-04": 44957.85,
    "2024-05": 52563.5,
    "2024-06": 48063.06,
    "2024-07": 54908.34,
    "2024-08": 51272.27,
    "2024-09": 47213.33,
    "2024-10": 44029.58,
    "2024-11": 36315.38,
    "2024-12": 24119.06,
    "2025-01": 29037.59,
    "2025-02": 39919.65,
    "2025-03": 45084.92,
    "2025-04": 47085.06,
    "2025-05": 33734.08,
    "2025-06": 39544.56,
    "2025-07": 41133.69,
    "2025-08": 43449.43,
    "2025-09": 41780.01,
    "2025-10": 55794.18,
    "2025-11": 37423.65,
    "2025-12": 37070.22,
    "2026-01": 31292.13,
    "2026-02": 35916.33,
    "2026-03": 7212.4,
    "2026-04": 468.84
  },
  "topCategory": {
    "category": "DESLOCAMENTO",
    "amountNet": 757725.08,
    "percent": 47.82
  }
}