{
  "meta": {
    "scope": "federal/camara",
    "type": "entity-profile",
    "entityId": 74848,
    "generatedAt": "2026-03-17T02:25:05.039659Z",
    "schemaVersion": "1.0.0"
  },
  "entity": {
    "id": 74848,
    "name": "Jandira Feghali",
    "stateCode": "RJ",
    "party": "PCdoB",
    "photoUrl": "https://www.camara.leg.br/internet/deputado/bandep/74848.jpg",
    "slug": "jandira-feghali"
  },
  "mandateTotals": {
    "amountNet": 395859.06,
    "amountGross": 431736.04,
    "amountAdjustments": -35876.98,
    "recordsCount": 342,
    "byCategoryNet": {
      "ALIMENTACAO": 0.0,
      "COMBUSTIVEL": 19241.43,
      "CONSULTORIA_SERVICOS": 0.0,
      "CORREIOS_TELEFONIA": 6101.94,
      "DESLOCAMENTO": 144574.84,
      "DIVULGACAO": 131668.0,
      "ESCRITORIO": 94272.85,
      "HOSPEDAGEM": 0.0,
      "OUTROS": 0.0
    },
    "byCategoryGross": {
      "ALIMENTACAO": 0.0,
      "COMBUSTIVEL": 19241.43,
      "CONSULTORIA_SERVICOS": 0.0,
      "CORREIOS_TELEFONIA": 6101.94,
      "DESLOCAMENTO": 180451.82,
      "DIVULGACAO": 131668.0,
      "ESCRITORIO": 94272.85,
      "HOSPEDAGEM": 0.0,
      "OUTROS": 0.0
    },
    "byCategoryAdjustments": {
      "ALIMENTACAO": 0.0,
      "COMBUSTIVEL": 0.0,
      "CONSULTORIA_SERVICOS": 0.0,
      "CORREIOS_TELEFONIA": 0.0,
      "DESLOCAMENTO": -35876.98,
      "DIVULGACAO": 0.0,
      "ESCRITORIO": 0.0,
      "HOSPEDAGEM": 0.0,
      "OUTROS": 0.0
    }
  },
  "yearTotals": {
    "2023": 395859.06
  },
  "monthTotals": {
    "2023-01": 9790.43,
    "2023-02": 33987.74,
    "2023-03": 36193.49,
    "2023-04": 33296.88,
    "2023-05": 36180.49,
    "2023-06": 39732.27,
    "2023-07": 34922.6,
    "2023-08": 33402.76,
    "2023-09": 32439.89,
    "2023-10": 48647.6,
    "2023-11": 23766.19,
    "2023-12": 33498.72
  },
  "topCategory": {
    "category": "DESLOCAMENTO",
    "amountNet": 144574.84,
    "percent": 36.52
  }
}