{
  "meta": {
    "tipo": "ranking_categoria",
    "escopo": "federal/camara",
    "categoriaQC": "HOSPEDAGEM",
    "periodo": {
      "tipo": "mes",
      "ano": 2025,
      "mes": 11
    },
    "geradoEm": "2026-03-07T16:32:21.249512Z",
    "versaoSchema": "2.0.0",
    "versaoCategoryMap": "1.0.0",
    "criterio": {
      "consideraAtivosNoPeriodo": true
    }
  },
  "itens": [
    {
      "id": 204411,
      "nome": "Filipe Barros",
      "uf": "PR",
      "partido": "PL",
      "valor": 14895.76,
      "valorLiquido": 14895.76,
      "valorBruto": 14895.76,
      "valorAjustes": 0.0,
      "qtdLancamentos": 40
    },
    {
      "id": 157130,
      "nome": "Túlio Gadêlha",
      "uf": "PE",
      "partido": "REDE",
      "valor": 12230.0,
      "valorLiquido": 12230.0,
      "valorBruto": 12230.0,
      "valorAjustes": 0.0,
      "qtdLancamentos": 42
    },
    {
      "id": 220527,
      "nome": "Jack Rocha",
      "uf": "ES",
      "partido": "PT",
      "valor": 12000.0,
      "valorLiquido": 12000.0,
      "valorBruto": 12000.0,
      "valorAjustes": 0.0,
      "qtdLancamentos": 28
    },
    {
      "id": 231911,
      "nome": "Lenir de Assis",
      "uf": "PR",
      "partido": "PT",
      "valor": 12000.0,
      "valorLiquido": 12000.0,
      "valorBruto": 12000.0,
      "valorAjustes": 0.0,
      "qtdLancamentos": 73
    },
    {
      "id": 220605,
      "nome": "Bandeira de Mello",
      "uf": "RJ",
      "partido": "PSB",
      "valor": 11857.5,
      "valorLiquido": 11857.5,
      "valorBruto": 11857.5,
      "valorAjustes": 0.0,
      "qtdLancamentos": 57
    },
    {
      "id": 73701,
      "nome": "Benedita da Silva",
      "uf": "RJ",
      "partido": "PT",
      "valor": 11334.0,
      "valorLiquido": 11334.0,
      "valorBruto": 11334.0,
      "valorAjustes": 0.0,
      "qtdLancamentos": 28
    },
    {
      "id": 220598,
      "nome": "Tarcísio Motta",
      "uf": "RJ",
      "partido": "PSOL",
      "valor": 10500.0,
      "valorLiquido": 10500.0,
      "valorBruto": 10500.0,
      "valorAjustes": 0.0,
      "qtdLancamentos": 82
    },
    {
      "id": 178866,
      "nome": "Luizianne Lins",
      "uf": "CE",
      "partido": "PT",
      "valor": 10482.22,
      "valorLiquido": 10482.22,
      "valorBruto": 10482.22,
      "valorAjustes": 0.0,
      "qtdLancamentos": 23
    },
    {
      "id": 160599,
      "nome": "Dimas Fabiano",
      "uf": "MG",
      "partido": "PP",
      "valor": 8813.52,
      "valorLiquido": 8813.52,
      "valorBruto": 8813.52,
      "valorAjustes": 0.0,
      "qtdLancamentos": 153
    },
    {
      "id": 226179,
      "nome": "Gisela Simona",
      "uf": "MT",
      "partido": "UNIÃO",
      "valor": 7211.9,
      "valorLiquido": 7211.9,
      "valorBruto": 7211.9,
      "valorAjustes": 0.0,
      "qtdLancamentos": 44
    }
  ]
}