{
  "meta": {
    "fonte": "Camara Dados Abertos",
    "escopo": "federal/camara",
    "periodo": {
      "ano": 2024,
      "mes": 9
    },
    "geradoEm": "2026-03-07T14:40:29.599717Z"
  },
  "data": [
    {
      "tipoDespesa": "DIVULGAÇÃO DA ATIVIDADE PARLAMENTAR.",
      "valorTotal": 5628937.88,
      "valorLiquido": 5628937.88,
      "valorBruto": 5628937.88,
      "valorAjustes": 0.0,
      "qtd": 1017
    },
    {
      "tipoDespesa": "LOCAÇÃO OU FRETAMENTO DE VEÍCULOS AUTOMOTORES",
      "valorTotal": 3143038.41,
      "valorLiquido": 3143038.41,
      "valorBruto": 3143038.41,
      "valorAjustes": 0.0,
      "qtd": 536
    },
    {
      "tipoDespesa": "MANUTENÇÃO DE ESCRITÓRIO DE APOIO À ATIVIDADE PARLAMENTAR",
      "valorTotal": 2374295.56,
      "valorLiquido": 2374295.56,
      "valorBruto": 2374295.56,
      "valorAjustes": 0.0,
      "qtd": 1502
    },
    {
      "tipoDespesa": "PASSAGEM AÉREA - SIGEPA",
      "valorTotal": 1938705.97,
      "valorLiquido": 1938705.97,
      "valorBruto": 2420247.54,
      "valorAjustes": -481541.57,
      "qtd": 2578
    },
    {
      "tipoDespesa": "COMBUSTÍVEIS E LUBRIFICANTES.",
      "valorTotal": 1697347.92,
      "valorLiquido": 1697347.92,
      "valorBruto": 1697347.92,
      "valorAjustes": 0.0,
      "qtd": 5338
    },
    {
      "tipoDespesa": "HOSPEDAGEM ,EXCETO DO PARLAMENTAR NO DISTRITO FEDERAL.",
      "valorTotal": 423200.61,
      "valorLiquido": 423200.61,
      "valorBruto": 423200.61,
      "valorAjustes": 0.0,
      "qtd": 1166
    },
    {
      "tipoDespesa": "LOCAÇÃO OU FRETAMENTO DE AERONAVES",
      "valorTotal": 219125.0,
      "valorLiquido": 219125.0,
      "valorBruto": 219125.0,
      "valorAjustes": 0.0,
      "qtd": 9
    },
    {
      "tipoDespesa": "TELEFONIA",
      "valorTotal": 155089.12,
      "valorLiquido": 155089.12,
      "valorBruto": 155089.12,
      "valorAjustes": 0.0,
      "qtd": 433
    },
    {
      "tipoDespesa": "SERVIÇO DE SEGURANÇA PRESTADO POR EMPRESA ESPECIALIZADA.",
      "valorTotal": 122494.3,
      "valorLiquido": 122494.3,
      "valorBruto": 122494.3,
      "valorAjustes": 0.0,
      "qtd": 37
    },
    {
      "tipoDespesa": "PASSAGEM AÉREA - RPA",
      "valorTotal": 106055.73,
      "valorLiquido": 106055.73,
      "valorBruto": 110890.76,
      "valorAjustes": -4835.03,
      "qtd": 73
    },
    {
      "tipoDespesa": "PASSAGEM AÉREA - REEMBOLSO",
      "valorTotal": 78787.51,
      "valorLiquido": 78787.51,
      "valorBruto": 78787.51,
      "valorAjustes": 0.0,
      "qtd": 26
    },
    {
      "tipoDespesa": "SERVIÇO DE TÁXI, PEDÁGIO E ESTACIONAMENTO",
      "valorTotal": 77213.71,
      "valorLiquido": 77213.71,
      "valorBruto": 77213.71,
      "valorAjustes": 0.0,
      "qtd": 1287
    },
    {
      "tipoDespesa": "FORNECIMENTO DE ALIMENTAÇÃO DO PARLAMENTAR",
      "valorTotal": 36520.2,
      "valorLiquido": 36520.2,
      "valorBruto": 36520.2,
      "valorAjustes": 0.0,
      "qtd": 518
    },
    {
      "tipoDespesa": "PASSAGENS TERRESTRES, MARÍTIMAS OU FLUVIAIS",
      "valorTotal": 9226.18,
      "valorLiquido": 9226.18,
      "valorBruto": 9226.18,
      "valorAjustes": 0.0,
      "qtd": 63
    },
    {
      "tipoDespesa": "ASSINATURA DE PUBLICAÇÕES",
      "valorTotal": 5730.64,
      "valorLiquido": 5730.64,
      "valorBruto": 5730.64,
      "valorAjustes": 0.0,
      "qtd": 18
    },
    {
      "tipoDespesa": "LOCAÇÃO OU FRETAMENTO DE EMBARCAÇÕES",
      "valorTotal": 3900.0,
      "valorLiquido": 3900.0,
      "valorBruto": 3900.0,
      "valorAjustes": 0.0,
      "qtd": 1
    },
    {
      "tipoDespesa": "AQUISIÇÃO DE TOKENS E CERTIFICADOS DIGITAIS",
      "valorTotal": 124.9,
      "valorLiquido": 124.9,
      "valorBruto": 124.9,
      "valorAjustes": 0.0,
      "qtd": 1
    }
  ]
}