{
  "meta": {
    "tipo": "ranking_total",
    "escopo": "federal/camara",
    "periodo": {
      "tipo": "mandato",
      "inicioAno": 2023,
      "fimAno": 2026,
      "totalMesesIncluidos": 13
    },
    "geradoEm": "2026-03-06T04:58:06.323627Z",
    "versaoSchema": "1.0.0",
    "versaoCategoryMap": "1.0.0",
    "criterio": {
      "consideraAtivosNoPeriodo": true
    }
  },
  "itens": [
    {
      "id": 204531,
      "nome": "Guilherme Derrite",
      "uf": "SP",
      "partido": "PP",
      "valor": 1638.0,
      "qtdLancamentos": 2
    },
    {
      "id": 234310,
      "nome": "Ricardo Galvão",
      "uf": "SP",
      "partido": "REDE",
      "valor": 6775.42,
      "qtdLancamentos": 8
    },
    {
      "id": 143084,
      "nome": "Tiago Dimas",
      "uf": "TO",
      "partido": "PODE",
      "valor": 12385.88,
      "qtdLancamentos": 23
    },
    {
      "id": 220715,
      "nome": "Amom Mandel",
      "uf": "AM",
      "partido": "CIDADANIA",
      "valor": 12966.5,
      "qtdLancamentos": 41
    },
    {
      "id": 141533,
      "nome": "Rodrigo Rollemberg",
      "uf": "DF",
      "partido": "PSB",
      "valor": 14396.59,
      "qtdLancamentos": 13
    },
    {
      "id": 234788,
      "nome": "Heloísa Helena",
      "uf": "RJ",
      "partido": "REDE",
      "valor": 19879.4,
      "qtdLancamentos": 1
    },
    {
      "id": 73788,
      "nome": "Ricardo Barros",
      "uf": "PR",
      "partido": "PP",
      "valor": 25942.7,
      "qtdLancamentos": 17
    },
    {
      "id": 230765,
      "nome": "Enfermeira Rejane",
      "uf": "RJ",
      "partido": "PCdoB",
      "valor": 26297.82,
      "qtdLancamentos": 5
    },
    {
      "id": 229585,
      "nome": "Elisangela Araujo",
      "uf": "BA",
      "partido": "PT",
      "valor": 26542.67,
      "qtdLancamentos": 23
    },
    {
      "id": 175765,
      "nome": "Ribamar Silva",
      "uf": "SP",
      "partido": "PSD",
      "valor": 26608.68,
      "qtdLancamentos": 21
    }
  ]
}