{
  "meta": {
    "escopo": "federal/camara",
    "tipo": "resumo_deputado_mandato",
    "id": 204431,
    "geradoEm": "2026-03-03T22:09:04.027019Z",
    "versaoSchema": "1.1.0"
  },
  "data": {
    "id": 204431,
    "nome": "Marcos Aurélio Sampaio",
    "uf": "PI",
    "partido": "PSD",
    "urlFoto": "https://www.camara.leg.br/internet/deputado/bandep/204431.jpg",
    "totaisMandato": {
      "total": 1712863.53,
      "qtdLancamentos": 332,
      "porCategoria": {
        "ALIMENTACAO": 0.0,
        "COMBUSTIVEL": 266047.71,
        "CONSULTORIA_SERVICOS": 0.0,
        "CORREIOS_TELEFONIA": 0.0,
        "DIVULGACAO": 802000.0,
        "ESCRITORIO": 53840.74,
        "HOSPEDAGEM": 0.0,
        "OUTROS": 432000.0,
        "PASSAGENS": 158975.08
      },
      "qtdSemDocumentoPdf": 221,
      "valorSemDocumentoPdf": 426287.99,
      "qtdRecibosOutros": 37,
      "valorRecibosOutros": 433275.0
    },
    "totaisAno": {
      "2023": 552802.19,
      "2024": 569921.49,
      "2025": 545939.85,
      "2026": 44200.0
    },
    "porMes": {
      "2023-01": 12227.3,
      "2023-02": 48725.64,
      "2023-03": 51954.07,
      "2023-04": 46213.42,
      "2023-05": 59443.05,
      "2023-06": 62422.49,
      "2023-07": 52506.74,
      "2023-08": 52792.85,
      "2023-09": 46759.36,
      "2023-10": 50171.6,
      "2023-11": 46569.51,
      "2023-12": 23016.16,
      "2024-01": 46009.51,
      "2024-02": 46236.1,
      "2024-03": 49121.41,
      "2024-04": 44398.01,
      "2024-05": 49312.58,
      "2024-06": 49343.23,
      "2024-07": 44200.0,
      "2024-08": 51482.72,
      "2024-09": 44200.0,
      "2024-10": 47894.9,
      "2024-11": 46884.41,
      "2024-12": 50838.62,
      "2025-01": 49572.15,
      "2025-02": 53540.56,
      "2025-03": 46682.24,
      "2025-04": 51997.1,
      "2025-05": 49329.51,
      "2025-06": 49890.33,
      "2025-07": 52721.12,
      "2025-08": 44300.0,
      "2025-09": 46406.84,
      "2025-10": 44300.0,
      "2025-11": 40200.0,
      "2025-12": 17000.0,
      "2026-01": 44200.0,
      "2026-02": 0.0,
      "2026-03": 0.0,
      "2026-04": 0.0,
      "2026-05": 0.0,
      "2026-06": 0.0,
      "2026-07": 0.0,
      "2026-08": 0.0,
      "2026-09": 0.0,
      "2026-10": 0.0,
      "2026-11": 0.0,
      "2026-12": 0.0
    },
    "maiorCategoria": {
      "categoria": "DIVULGACAO",
      "valor": 802000.0,
      "pct": 46.82
    }
  }
}