{
  "meta": {
    "escopo": "federal/camara",
    "tipo": "resumo_deputado_mandato",
    "id": 204408,
    "geradoEm": "2026-03-06T04:58:06.452579Z",
    "versaoSchema": "1.1.0"
  },
  "data": {
    "id": 204408,
    "nome": "Gustinho Ribeiro",
    "uf": "SE",
    "partido": "REPUBLICANOS",
    "urlFoto": "https://www.camara.leg.br/internet/deputado/bandep/204408.jpg",
    "totaisMandato": {
      "total": 525011.71,
      "qtdLancamentos": 144,
      "porCategoria": {
        "ALIMENTACAO": 0.0,
        "COMBUSTIVEL": 0.0,
        "CONSULTORIA_SERVICOS": 0.0,
        "CORREIOS_TELEFONIA": 0.0,
        "DIVULGACAO": 276900.0,
        "ESCRITORIO": 6800.0,
        "HOSPEDAGEM": 0.0,
        "OUTROS": 0.0,
        "PASSAGENS": 241311.71
      },
      "qtdSemDocumentoPdf": 118,
      "valorSemDocumentoPdf": 120811.71,
      "qtdRecibosOutros": 9,
      "valorRecibosOutros": 120500.0
    },
    "totaisAno": {
      "2023": 491111.71,
      "2026": 33900.0
    },
    "porMes": {
      "2023-01": 0.0,
      "2023-02": 26465.87,
      "2023-03": 21871.13,
      "2023-04": 28488.2,
      "2023-05": 40224.96,
      "2023-06": 39286.38,
      "2023-07": 50413.47,
      "2023-08": 18975.52,
      "2023-09": 32705.92,
      "2023-10": 17235.58,
      "2023-11": 25456.45,
      "2023-12": 189988.23,
      "2026-01": 33900.0
    },
    "maiorCategoria": {
      "categoria": "DIVULGACAO",
      "valor": 276900.0,
      "pct": 52.74
    }
  }
}