{
  "meta": {
    "escopo": "federal/camara",
    "tipo": "resumo_deputado_mandato",
    "id": 214694,
    "geradoEm": "2026-03-06T12:37:52.641869Z",
    "versaoSchema": "1.1.0"
  },
  "data": {
    "id": 214694,
    "nome": "Jorge Goetten",
    "uf": "SC",
    "partido": "REPUBLICANOS",
    "urlFoto": "https://www.camara.leg.br/internet/deputado/bandep/214694.jpg",
    "totaisMandato": {
      "total": 956138.72,
      "qtdLancamentos": 982,
      "porCategoria": {
        "ALIMENTACAO": 642.32,
        "COMBUSTIVEL": 147072.78,
        "CONSULTORIA_SERVICOS": 0.0,
        "CORREIOS_TELEFONIA": 1281.63,
        "DESLOCAMENTO": 387427.95,
        "DIVULGACAO": 229126.99,
        "ESCRITORIO": 178963.87,
        "HOSPEDAGEM": 11623.18,
        "OUTROS": 0.0
      },
      "qtdSemDocumentoPdf": 640,
      "valorSemDocumentoPdf": 390938.95,
      "qtdRecibosOutros": 71,
      "valorRecibosOutros": 268530.76
    },
    "totaisAno": {
      "2023": 464944.61,
      "2024": 491194.11
    },
    "porMes": {
      "2023-01": 0.0,
      "2023-02": 32701.68,
      "2023-03": 50463.71,
      "2023-04": 41068.87,
      "2023-05": 32272.79,
      "2023-06": 36289.35,
      "2023-07": 30934.24,
      "2023-08": 52760.15,
      "2023-09": 58282.57,
      "2023-10": 48155.39,
      "2023-11": 45376.92,
      "2023-12": 36638.94,
      "2024-01": 45347.96,
      "2024-02": 70832.14,
      "2024-03": 44228.76,
      "2024-04": 51226.74,
      "2024-05": 43052.38,
      "2024-06": 57971.13,
      "2024-07": 40186.83,
      "2024-08": 31375.29,
      "2024-09": 31757.45,
      "2024-10": 22243.8,
      "2024-11": 35206.22,
      "2024-12": 17765.41
    },
    "maiorCategoria": {
      "categoria": "DESLOCAMENTO",
      "valor": 387427.95,
      "pct": 40.52
    }
  }
}