{
  "meta": {
    "escopo": "federal/camara",
    "tipo": "resumo_deputado_mandato",
    "id": 220602,
    "geradoEm": "2026-03-06T12:37:52.620411Z",
    "versaoSchema": "1.1.0"
  },
  "data": {
    "id": 220602,
    "nome": "Dimas Gadelha",
    "uf": "RJ",
    "partido": "PT",
    "urlFoto": "https://www.camara.leg.br/internet/deputado/bandep/220602.jpg",
    "totaisMandato": {
      "total": 929538.24,
      "qtdLancamentos": 337,
      "porCategoria": {
        "ALIMENTACAO": 83.37,
        "COMBUSTIVEL": 18757.31,
        "CONSULTORIA_SERVICOS": 0.0,
        "CORREIOS_TELEFONIA": 0.0,
        "DESLOCAMENTO": 237255.81,
        "DIVULGACAO": 549198.52,
        "ESCRITORIO": 124243.23,
        "HOSPEDAGEM": 0.0,
        "OUTROS": 0.0
      },
      "qtdSemDocumentoPdf": 263,
      "valorSemDocumentoPdf": 169101.27,
      "qtdRecibosOutros": 25,
      "valorRecibosOutros": 119504.25
    },
    "totaisAno": {
      "2023": 445259.96,
      "2024": 484278.28
    },
    "porMes": {
      "2023-01": 0.0,
      "2023-02": 28953.05,
      "2023-03": 46211.42,
      "2023-04": 31367.57,
      "2023-05": 24154.7,
      "2023-06": 27434.34,
      "2023-07": 34601.88,
      "2023-08": 28655.87,
      "2023-09": 35519.3,
      "2023-10": 45733.05,
      "2023-11": 46863.71,
      "2023-12": 95765.07,
      "2024-01": 43309.51,
      "2024-02": 43797.77,
      "2024-03": 38986.42,
      "2024-04": 26210.4,
      "2024-05": 67169.55,
      "2024-06": 10689.54,
      "2024-07": 1870.08,
      "2024-08": 7501.99,
      "2024-09": 20819.8,
      "2024-10": 48401.31,
      "2024-11": 95453.29,
      "2024-12": 80068.62
    },
    "maiorCategoria": {
      "categoria": "DIVULGACAO",
      "valor": 549198.52,
      "pct": 59.08
    }
  }
}