{
  "meta": {
    "escopo": "federal/camara",
    "tipo": "resumo_deputado_mandato",
    "id": 223128,
    "geradoEm": "2026-03-06T04:58:06.491386Z",
    "versaoSchema": "1.1.0"
  },
  "data": {
    "id": 223128,
    "nome": "Rodrigo Estacho",
    "uf": "PR",
    "partido": "PSD",
    "urlFoto": "https://www.camara.leg.br/internet/deputado/bandep/223128.jpg",
    "totaisMandato": {
      "total": 414163.55,
      "qtdLancamentos": 802,
      "porCategoria": {
        "ALIMENTACAO": 0.0,
        "COMBUSTIVEL": 87718.05,
        "CONSULTORIA_SERVICOS": 0.0,
        "CORREIOS_TELEFONIA": 2702.8,
        "DIVULGACAO": 49679.72,
        "ESCRITORIO": 87598.23,
        "HOSPEDAGEM": 13878.82,
        "OUTROS": 0.0,
        "PASSAGENS": 172585.93
      },
      "qtdSemDocumentoPdf": 614,
      "valorSemDocumentoPdf": 190489.81,
      "qtdRecibosOutros": 59,
      "valorRecibosOutros": 158084.66
    },
    "totaisAno": {
      "2023": 382057.14,
      "2026": 32106.41
    },
    "porMes": {
      "2023-01": 0.0,
      "2023-02": 4384.86,
      "2023-03": 38628.07,
      "2023-04": 32541.28,
      "2023-05": 33783.32,
      "2023-06": 34649.09,
      "2023-07": 45055.2,
      "2023-08": 45050.92,
      "2023-09": 35947.29,
      "2023-10": 44139.25,
      "2023-11": 34221.76,
      "2023-12": 33656.1,
      "2026-01": 32106.41
    },
    "maiorCategoria": {
      "categoria": "PASSAGENS",
      "valor": 172585.93,
      "pct": 41.67
    }
  }
}