{
  "meta": {
    "escopo": "federal/camara",
    "tipo": "resumo_deputado_mandato",
    "id": 74848,
    "geradoEm": "2026-03-07T14:55:24.192928Z",
    "versaoSchema": "2.0.0"
  },
  "data": {
    "id": 74848,
    "nome": "Jandira Feghali",
    "uf": "RJ",
    "partido": "PCdoB",
    "urlFoto": "https://www.camara.leg.br/internet/deputado/bandep/74848.jpg",
    "totaisMandato": {
      "total": 774469.78,
      "totalLiquido": 774469.78,
      "totalBruto": 860852.19,
      "totalAjustes": -86382.41,
      "qtdLancamentos": 653,
      "porCategoria": {
        "ALIMENTACAO": 0.0,
        "COMBUSTIVEL": 37830.21,
        "CONSULTORIA_SERVICOS": 0.0,
        "CORREIOS_TELEFONIA": 9730.48,
        "DESLOCAMENTO": 254979.66,
        "DIVULGACAO": 259756.0,
        "ESCRITORIO": 212173.43,
        "HOSPEDAGEM": 0.0,
        "OUTROS": 0.0
      },
      "porCategoriaLiquido": {
        "ALIMENTACAO": 0.0,
        "COMBUSTIVEL": 37830.21,
        "CONSULTORIA_SERVICOS": 0.0,
        "CORREIOS_TELEFONIA": 9730.48,
        "DESLOCAMENTO": 254979.66,
        "DIVULGACAO": 259756.0,
        "ESCRITORIO": 212173.43,
        "HOSPEDAGEM": 0.0,
        "OUTROS": 0.0
      },
      "porCategoriaBruto": {
        "ALIMENTACAO": 0.0,
        "COMBUSTIVEL": 37830.21,
        "CONSULTORIA_SERVICOS": 0.0,
        "CORREIOS_TELEFONIA": 9730.48,
        "DESLOCAMENTO": 341362.07,
        "DIVULGACAO": 259756.0,
        "ESCRITORIO": 212173.43,
        "HOSPEDAGEM": 0.0,
        "OUTROS": 0.0
      },
      "porCategoriaAjustes": {
        "ALIMENTACAO": 0.0,
        "COMBUSTIVEL": 0.0,
        "CONSULTORIA_SERVICOS": 0.0,
        "CORREIOS_TELEFONIA": 0.0,
        "DESLOCAMENTO": -86382.41,
        "DIVULGACAO": 0.0,
        "ESCRITORIO": 0.0,
        "HOSPEDAGEM": 0.0,
        "OUTROS": 0.0
      }
    },
    "totaisAno": {
      "2023": 395859.06,
      "2024": 378610.72
    },
    "porMes": {
      "2023-01": 9790.43,
      "2023-02": 33987.74,
      "2023-03": 36193.49,
      "2023-04": 33296.88,
      "2023-05": 36180.49,
      "2023-06": 39732.27,
      "2023-07": 34922.6,
      "2023-08": 33402.76,
      "2023-09": 32439.89,
      "2023-10": 48647.6,
      "2023-11": 23766.19,
      "2023-12": 33498.72,
      "2024-01": 21834.67,
      "2024-02": 31807.46,
      "2024-03": 31094.89,
      "2024-04": 27449.89,
      "2024-05": 41037.64,
      "2024-06": 35886.79,
      "2024-07": 27070.96,
      "2024-08": 27929.38,
      "2024-09": 26674.8,
      "2024-10": 39103.21,
      "2024-11": 37306.41,
      "2024-12": 31414.62
    },
    "maiorCategoria": {
      "categoria": "DIVULGACAO",
      "valor": 259756.0,
      "pct": 33.54
    }
  }
}