{
  "meta": {
    "tipo": "ranking_categoria",
    "escopo": "federal/camara",
    "categoriaQC": "ESCRITORIO",
    "periodo": {
      "tipo": "mes",
      "ano": 2025,
      "mes": 2
    },
    "geradoEm": "2026-03-04T18:24:08.557316Z",
    "versaoSchema": "1.0.0",
    "versaoCategoryMap": "1.0.0",
    "criterio": {
      "consideraAtivosNoPeriodo": true
    }
  },
  "itens": [
    {
      "id": 166402,
      "nome": "Magda Mofatto",
      "uf": "GO",
      "partido": "PRD",
      "valor": 32112.68,
      "qtdLancamentos": 28
    },
    {
      "id": 224117,
      "nome": "Gabriel Mota",
      "uf": "RR",
      "partido": "REPUBLICANOS",
      "valor": 29500.0,
      "qtdLancamentos": 6
    },
    {
      "id": 160665,
      "nome": "Augusto Coutinho",
      "uf": "PE",
      "partido": "REPUBLICANOS",
      "valor": 21781.41,
      "qtdLancamentos": 45
    },
    {
      "id": 204390,
      "nome": "Professor Alcides",
      "uf": "GO",
      "partido": "PL",
      "valor": 20764.0,
      "qtdLancamentos": 5
    },
    {
      "id": 204508,
      "nome": "Igor Timo",
      "uf": "MG",
      "partido": "PSD",
      "valor": 20763.36,
      "qtdLancamentos": 41
    },
    {
      "id": 141391,
      "nome": "Arnaldo Jardim",
      "uf": "SP",
      "partido": "CIDADANIA",
      "valor": 20582.74,
      "qtdLancamentos": 78
    },
    {
      "id": 220558,
      "nome": "Zé Trovão",
      "uf": "SC",
      "partido": "PL",
      "valor": 20226.16,
      "qtdLancamentos": 42
    },
    {
      "id": 74253,
      "nome": "Julio Lopes",
      "uf": "RJ",
      "partido": "PP",
      "valor": 20045.03,
      "qtdLancamentos": 20
    },
    {
      "id": 178992,
      "nome": "Vitor Lippi",
      "uf": "SP",
      "partido": "PSDB",
      "valor": 19589.76,
      "qtdLancamentos": 82
    },
    {
      "id": 74273,
      "nome": "Jefferson Campos",
      "uf": "SP",
      "partido": "PL",
      "valor": 19418.66,
      "qtdLancamentos": 47
    }
  ]
}