{
  "meta": {
    "tipo": "overview",
    "escopo": "federal/camara",
    "periodo": {
      "tipo": "mes",
      "ano": 2026,
      "mes": 2
    },
    "geradoEm": "2026-03-03T23:27:43.502300Z",
    "versaoSchema": "1.0.0",
    "versaoCategoryMap": "1.0.0"
  },
  "kpis": {
    "totalGasto": 6377187.91,
    "top1Gasto": {
      "id": 141459,
      "nome": "João Maia",
      "uf": "RN",
      "partido": "PP",
      "valor": 57616.68
    },
    "topCategorias": [
      {
        "categoriaQC": "DIVULGACAO",
        "valor": 3164991.01
      },
      {
        "categoriaQC": "ESCRITORIO",
        "valor": 1074575.64
      },
      {
        "categoriaQC": "COMBUSTIVEL",
        "valor": 954400.87
      },
      {
        "categoriaQC": "OUTROS",
        "valor": 953297.57
      },
      {
        "categoriaQC": "DEMAIS CATEGORIAS",
        "valor": 229922.82
      }
    ],
    "topUFs": [
      {
        "uf": "SP",
        "valor": 801706.76
      },
      {
        "uf": "BA",
        "valor": 568282.82
      },
      {
        "uf": "RS",
        "valor": 496640.73
      },
      {
        "uf": "MG",
        "valor": 471679.19
      },
      {
        "uf": "PR",
        "valor": 467561.14
      },
      {
        "uf": "RJ",
        "valor": 423575.85
      },
      {
        "uf": "CE",
        "valor": 306585.31
      },
      {
        "uf": "PB",
        "valor": 305015.75
      },
      {
        "uf": "PE",
        "valor": 280016.05
      },
      {
        "uf": "GO",
        "valor": 198729.89
      },
      {
        "uf": "MS",
        "valor": 177007.12
      },
      {
        "uf": "AC",
        "valor": 168081.63
      }
    ],
    "agentesConsiderados": 456
  }
}