{
  "meta": {
    "tipo": "ranking_categoria",
    "escopo": "federal/camara",
    "categoriaQC": "DESLOCAMENTO",
    "periodo": {
      "tipo": "mes",
      "ano": 2025,
      "mes": 9
    },
    "geradoEm": "2026-03-07T16:23:07.940446Z",
    "versaoSchema": "2.0.0",
    "versaoCategoryMap": "1.0.0",
    "criterio": {
      "consideraAtivosNoPeriodo": true
    }
  },
  "itens": [
    {
      "id": 74090,
      "nome": "Átila Lins",
      "uf": "AM",
      "partido": "PSD",
      "valor": 50671.82,
      "valorLiquido": 50671.82,
      "valorBruto": 50671.82,
      "valorAjustes": 0.0,
      "qtdLancamentos": 9
    },
    {
      "id": 178983,
      "nome": "Marcio Alvino",
      "uf": "SP",
      "partido": "PL",
      "valor": 44900.95,
      "valorLiquido": 44900.95,
      "valorBruto": 44900.95,
      "valorAjustes": 0.0,
      "qtdLancamentos": 99
    },
    {
      "id": 153423,
      "nome": "Renilce Nicodemos",
      "uf": "PA",
      "partido": "MDB",
      "valor": 43376.72,
      "valorLiquido": 43376.72,
      "valorBruto": 43376.72,
      "valorAjustes": 0.0,
      "qtdLancamentos": 12
    },
    {
      "id": 74079,
      "nome": "José Priante",
      "uf": "PA",
      "partido": "MDB",
      "valor": 39817.72,
      "valorLiquido": 39817.72,
      "valorBruto": 39817.72,
      "valorAjustes": 0.0,
      "qtdLancamentos": 14
    },
    {
      "id": 178854,
      "nome": "Elmar Nascimento",
      "uf": "BA",
      "partido": "UNIÃO",
      "valor": 35469.97,
      "valorLiquido": 35469.97,
      "valorBruto": 35469.97,
      "valorAjustes": 0.0,
      "qtdLancamentos": 13
    },
    {
      "id": 204574,
      "nome": "Junior Lourenço",
      "uf": "MA",
      "partido": "PL",
      "valor": 35337.11,
      "valorLiquido": 35337.11,
      "valorBruto": 35337.11,
      "valorAjustes": 0.0,
      "qtdLancamentos": 23
    },
    {
      "id": 204550,
      "nome": "Júnior Mano",
      "uf": "CE",
      "partido": "PSB",
      "valor": 32980.35,
      "valorLiquido": 32980.35,
      "valorBruto": 38636.08,
      "valorAjustes": -5655.73,
      "qtdLancamentos": 17
    },
    {
      "id": 178908,
      "nome": "Delegado Éder Mauro",
      "uf": "PA",
      "partido": "PL",
      "valor": 31481.22,
      "valorLiquido": 31481.22,
      "valorBruto": 35280.3,
      "valorAjustes": -3799.08,
      "qtdLancamentos": 14
    },
    {
      "id": 171617,
      "nome": "Paulão",
      "uf": "AL",
      "partido": "PT",
      "valor": 31418.21,
      "valorLiquido": 31418.21,
      "valorBruto": 31418.21,
      "valorAjustes": 0.0,
      "qtdLancamentos": 38
    },
    {
      "id": 141518,
      "nome": "Paulinho da Força",
      "uf": "SP",
      "partido": "SOLIDARIEDADE",
      "valor": 30734.39,
      "valorLiquido": 30734.39,
      "valorBruto": 39818.08,
      "valorAjustes": -9083.69,
      "qtdLancamentos": 37
    }
  ]
}