{
  "meta": {
    "tipo": "ranking_categoria",
    "escopo": "federal/camara",
    "categoriaQC": "PASSAGENS",
    "periodo": {
      "tipo": "mes",
      "ano": 2025,
      "mes": 4
    },
    "geradoEm": "2026-03-05T09:52:59.437160Z",
    "versaoSchema": "1.0.0",
    "versaoCategoryMap": "1.0.0",
    "criterio": {
      "consideraAtivosNoPeriodo": true
    }
  },
  "itens": [
    {
      "id": 220675,
      "nome": "Antônio Doido",
      "uf": "PA",
      "partido": "MDB",
      "valor": 82440.05,
      "qtdLancamentos": 21
    },
    {
      "id": 153423,
      "nome": "Renilce Nicodemos",
      "uf": "PA",
      "partido": "MDB",
      "valor": 68262.88,
      "qtdLancamentos": 22
    },
    {
      "id": 204427,
      "nome": "Fernando Rodolfo",
      "uf": "PE",
      "partido": "PL",
      "valor": 46931.55,
      "qtdLancamentos": 62
    },
    {
      "id": 220527,
      "nome": "Jack Rocha",
      "uf": "ES",
      "partido": "PT",
      "valor": 46707.12,
      "qtdLancamentos": 41
    },
    {
      "id": 220712,
      "nome": "Fausto Jr.",
      "uf": "AM",
      "partido": "UNIÃO",
      "valor": 44816.89,
      "qtdLancamentos": 25
    },
    {
      "id": 74161,
      "nome": "Reginaldo Lopes",
      "uf": "MG",
      "partido": "PT",
      "valor": 44745.47,
      "qtdLancamentos": 38
    },
    {
      "id": 204450,
      "nome": "Doutor Luizinho",
      "uf": "RJ",
      "partido": "PP",
      "valor": 41794.79,
      "qtdLancamentos": 41
    },
    {
      "id": 204404,
      "nome": "Lucas Redecker",
      "uf": "RS",
      "partido": "PSDB",
      "valor": 40484.25,
      "qtdLancamentos": 82
    },
    {
      "id": 160510,
      "nome": "Luis Tibé",
      "uf": "MG",
      "partido": "AVANTE",
      "valor": 39952.37,
      "qtdLancamentos": 71
    },
    {
      "id": 160642,
      "nome": "Pastor Eurico",
      "uf": "PE",
      "partido": "PL",
      "valor": 39046.16,
      "qtdLancamentos": 56
    }
  ]
}