{
  "meta": {
    "escopo": "federal/camara",
    "tipo": "resumo_index_deputados",
    "geradoEm": "2026-03-03T15:34:13.276573Z",
    "versaoSchema": "1.1.0",
    "mandatoInicioAno": 2023,
    "mandatoFimAno": 2026,
    "shard": {
      "tipo": "uf",
      "valor": "MS"
    }
  },
  "data": [
    {
      "id": 204358,
      "nome": "Beto Pereira",
      "uf": "MS",
      "partido": "PSDB",
      "urlFoto": "https://www.camara.leg.br/internet/deputado/bandep/204358.jpg",
      "totalMandato": 1757058.46,
      "totaisAno": {
        "2023": 596767.29,
        "2024": 543041.43,
        "2025": 557584.3,
        "2026": 59665.44
      },
      "metricas": {
        "variacaoMensalCV": 0.425751,
        "picoMes": "2024-12",
        "picoValor": 116534.76,
        "fornecedorTop1Pct": 0.022765,
        "fornecedorTop3Pct": 0.030395,
        "fornecedorHHI": 0.00055,
        "categoriaDominante": "DIVULGACAO",
        "categoriaDominantePct": 0.463364,
        "semDocumentoPct": 0.255939,
        "recibosOutrosPct": 0.229093
      },
      "flags": []
    },
    {
      "id": 220548,
      "nome": "Camila Jara",
      "uf": "MS",
      "partido": "PT",
      "urlFoto": "https://www.camara.leg.br/internet/deputado/bandep/220548.jpg",
      "totalMandato": 1659360.71,
      "totaisAno": {
        "2023": 513822.43,
        "2024": 549396.26,
        "2025": 534111.19,
        "2026": 62030.83
      },
      "metricas": {
        "variacaoMensalCV": 0.352301,
        "picoMes": "2024-11",
        "picoValor": 92880.21,
        "fornecedorTop1Pct": 0.022298,
        "fornecedorTop3Pct": 0.02909,
        "fornecedorHHI": 0.00053,
        "categoriaDominante": "DIVULGACAO",
        "categoriaDominantePct": 0.450612,
        "semDocumentoPct": 0.245666,
        "recibosOutrosPct": 0.221068
      },
      "flags": []
    },
    {
      "id": 141411,
      "nome": "Dagoberto Nogueira",
      "uf": "MS",
      "partido": "PSDB",
      "urlFoto": "https://www.camara.leg.br/internet/deputado/bandep/141411.jpg",
      "totalMandato": 1674293.35,
      "totaisAno": {
        "2023": 501965.41,
        "2024": 558589.43,
        "2025": 535668.17,
        "2026": 78070.34
      },
      "metricas": {
        "variacaoMensalCV": 0.366664,
        "picoMes": "2023-12",
        "picoValor": 114098.27,
        "fornecedorTop1Pct": 0.015241,
        "fornecedorTop3Pct": 0.034951,
        "fornecedorHHI": 0.000483,
        "categoriaDominante": "DIVULGACAO",
        "categoriaDominantePct": 0.393749,
        "semDocumentoPct": 0.207929,
        "recibosOutrosPct": 0.349638
      },
      "flags": [
        "high_receipts_other"
      ]
    },
    {
      "id": 204351,
      "nome": "Dr. Luiz Ovando",
      "uf": "MS",
      "partido": "PP",
      "urlFoto": "https://www.camara.leg.br/internet/deputado/bandep/204351.jpg",
      "totalMandato": 1620328.08,
      "totaisAno": {
        "2023": 528035.59,
        "2024": 523597.42,
        "2025": 523862.84,
        "2026": 44832.23
      },
      "metricas": {
        "variacaoMensalCV": 0.388972,
        "picoMes": "2024-12",
        "picoValor": 111411.52,
        "fornecedorTop1Pct": 0.007714,
        "fornecedorTop3Pct": 0.018702,
        "fornecedorHHI": 0.000135,
        "categoriaDominante": "DIVULGACAO",
        "categoriaDominantePct": 0.362425,
        "semDocumentoPct": 0.238777,
        "recibosOutrosPct": 0.385996
      },
      "flags": [
        "high_receipts_other"
      ]
    },
    {
      "id": 74374,
      "nome": "Geraldo Resende",
      "uf": "MS",
      "partido": "PSDB",
      "urlFoto": "https://www.camara.leg.br/internet/deputado/bandep/74374.jpg",
      "totalMandato": 1719873.19,
      "totaisAno": {
        "2023": 524343.8,
        "2024": 574031.55,
        "2025": 564425.04,
        "2026": 57072.8
      },
      "metricas": {
        "variacaoMensalCV": 0.393194,
        "picoMes": "2025-08",
        "picoValor": 75569.8,
        "fornecedorTop1Pct": 0.007268,
        "fornecedorTop3Pct": 0.017734,
        "fornecedorHHI": 0.000139,
        "categoriaDominante": "DIVULGACAO",
        "categoriaDominantePct": 0.533364,
        "semDocumentoPct": 0.19659,
        "recibosOutrosPct": 0.236608
      },
      "flags": []
    },
    {
      "id": 220547,
      "nome": "Marcos Pollon",
      "uf": "MS",
      "partido": "PL",
      "urlFoto": "https://www.camara.leg.br/internet/deputado/bandep/220547.jpg",
      "totalMandato": 1546811.89,
      "totaisAno": {
        "2023": 491252.85,
        "2024": 499747.44,
        "2025": 520570.52,
        "2026": 35241.08
      },
      "metricas": {
        "variacaoMensalCV": 0.521632,
        "picoMes": "2024-12",
        "picoValor": 95409.86,
        "fornecedorTop1Pct": 0.008275,
        "fornecedorTop3Pct": 0.018994,
        "fornecedorHHI": 0.000145,
        "categoriaDominante": "DIVULGACAO",
        "categoriaDominantePct": 0.563617,
        "semDocumentoPct": 0.240653,
        "recibosOutrosPct": 0.077501
      },
      "flags": []
    },
    {
      "id": 220546,
      "nome": "Rodolfo Nogueira",
      "uf": "MS",
      "partido": "PL",
      "urlFoto": "https://www.camara.leg.br/internet/deputado/bandep/220546.jpg",
      "totalMandato": 1686755.58,
      "totaisAno": {
        "2023": 520642.09,
        "2024": 555486.91,
        "2025": 567675.9,
        "2026": 42950.68
      },
      "metricas": {
        "variacaoMensalCV": 0.428988,
        "picoMes": "2024-12",
        "picoValor": 118301.34,
        "fornecedorTop1Pct": 0.008893,
        "fornecedorTop3Pct": 0.018859,
        "fornecedorHHI": 0.000145,
        "categoriaDominante": "DIVULGACAO",
        "categoriaDominantePct": 0.494771,
        "semDocumentoPct": 0.181028,
        "recibosOutrosPct": 0.276871
      },
      "flags": []
    },
    {
      "id": 74376,
      "nome": "Vander Loubet",
      "uf": "MS",
      "partido": "PT",
      "urlFoto": "https://www.camara.leg.br/internet/deputado/bandep/74376.jpg",
      "totalMandato": 1628167.97,
      "totaisAno": {
        "2023": 542666.51,
        "2024": 488383.99,
        "2025": 531964.91,
        "2026": 65152.56
      },
      "metricas": {
        "variacaoMensalCV": 0.277638,
        "picoMes": "2024-03",
        "picoValor": 65752.73,
        "fornecedorTop1Pct": 0.012252,
        "fornecedorTop3Pct": 0.033853,
        "fornecedorHHI": 0.000391,
        "categoriaDominante": "DIVULGACAO",
        "categoriaDominantePct": 0.433905,
        "semDocumentoPct": 0.23735,
        "recibosOutrosPct": 0.255057
      },
      "flags": []
    }
  ]
}