{
  "meta": {
    "tipo": "ranking_total",
    "escopo": "federal/camara",
    "periodo": {
      "tipo": "mes",
      "ano": 2023,
      "mes": 7
    },
    "geradoEm": "2026-03-06T10:55:33.622795Z",
    "versaoSchema": "1.0.0",
    "versaoCategoryMap": "1.0.0",
    "criterio": {
      "consideraAtivosNoPeriodo": true
    }
  },
  "itens": [
    {
      "id": 220715,
      "nome": "Amom Mandel",
      "uf": "AM",
      "partido": "CIDADANIA",
      "valor": 0.0,
      "qtdLancamentos": 2
    },
    {
      "id": 178983,
      "nome": "Marcio Alvino",
      "uf": "SP",
      "partido": "PL",
      "valor": 1691.65,
      "qtdLancamentos": 6
    },
    {
      "id": 204528,
      "nome": "Adriana Ventura",
      "uf": "SP",
      "partido": "NOVO",
      "valor": 1752.55,
      "qtdLancamentos": 16
    },
    {
      "id": 204459,
      "nome": "Daniela do Waguinho",
      "uf": "RJ",
      "partido": "UNIÃO",
      "valor": 1935.0,
      "qtdLancamentos": 1
    },
    {
      "id": 160541,
      "nome": "Arthur Lira",
      "uf": "AL",
      "partido": "PP",
      "valor": 2183.04,
      "qtdLancamentos": 9
    },
    {
      "id": 74356,
      "nome": "Silas Câmara",
      "uf": "AM",
      "partido": "REPUBLICANOS",
      "valor": 3259.0,
      "qtdLancamentos": 2
    },
    {
      "id": 204365,
      "nome": "Gilson Marques",
      "uf": "SC",
      "partido": "NOVO",
      "valor": 4809.31,
      "qtdLancamentos": 15
    },
    {
      "id": 204570,
      "nome": "Pastor Gil",
      "uf": "MA",
      "partido": "PL",
      "valor": 6657.36,
      "qtdLancamentos": 13
    },
    {
      "id": 220528,
      "nome": "Dr. Victor Linhalis",
      "uf": "ES",
      "partido": "PODE",
      "valor": 6819.83,
      "qtdLancamentos": 16
    },
    {
      "id": 178946,
      "nome": "Soraya Santos",
      "uf": "RJ",
      "partido": "PL",
      "valor": 6910.78,
      "qtdLancamentos": 12
    }
  ]
}