{
  "meta": {
    "tipo": "overview",
    "escopo": "federal/camara",
    "periodo": {
      "tipo": "mes",
      "ano": 2023,
      "mes": 11
    },
    "geradoEm": "2026-03-01T15:13:48.844415Z",
    "versaoSchema": "1.0.0",
    "versaoCategoryMap": "1.0.0"
  },
  "kpis": {
    "totalGasto": 21032284.15,
    "top1Gasto": {
      "id": 178881,
      "nome": "Aluisio Mendes",
      "uf": "MA",
      "partido": "REPUBLICANOS",
      "valor": 182364.83
    },
    "topCategorias": [
      {
        "categoriaQC": "DIVULGACAO",
        "valor": 8885044.11
      },
      {
        "categoriaQC": "PASSAGENS",
        "valor": 3780984.94
      },
      {
        "categoriaQC": "OUTROS",
        "valor": 3409555.84
      },
      {
        "categoriaQC": "ESCRITORIO",
        "valor": 2664614.47
      },
      {
        "categoriaQC": "DEMAIS CATEGORIAS",
        "valor": 2292084.79
      }
    ],
    "topUFs": [
      {
        "uf": "SP",
        "valor": 2510091.48
      },
      {
        "uf": "MG",
        "valor": 2190881.25
      },
      {
        "uf": "BA",
        "valor": 1689558.13
      },
      {
        "uf": "RJ",
        "valor": 1644104.84
      },
      {
        "uf": "PR",
        "valor": 1335043.24
      },
      {
        "uf": "RS",
        "valor": 1332454.15
      },
      {
        "uf": "PE",
        "valor": 1203647.33
      },
      {
        "uf": "CE",
        "valor": 823387.32
      },
      {
        "uf": "PA",
        "valor": 802218.27
      },
      {
        "uf": "MA",
        "valor": 795883.29
      },
      {
        "uf": "PB",
        "valor": 606334.76
      },
      {
        "uf": "GO",
        "valor": 595616.59
      }
    ],
    "agentesConsiderados": 470
  }
}